BotingTools/BotingTools.py
BotingTools/__init__.py
botingtools-1.2.0.dist-info/METADATA
botingtools-1.2.0.dist-info/WHEEL
botingtools-1.2.0.dist-info/top_level.txt
botingtools-1.2.0.dist-info/RECORD
