Metadata-Version: 2.4
Name: BotingTools
Version: 1.2.0
Summary: AI-powered automation and video generation toolkit
Author: Dinis Valente
Author-email: Dinis <your.email@example.com>
License: MIT
Requires-Python: >=3.10
Requires-Dist: gpt4all
Requires-Dist: selenium
Requires-Dist: undetected_chromedriver
Requires-Dist: random_username
Requires-Dist: bs4
Requires-Dist: typing
Requires-Dist: selenium_recaptcha_solver
Requires-Dist: fake_useragent
Requires-Dist: stackapi
Requires-Dist: Pillow
Requires-Dist: moviepy
Requires-Dist: seleniumbase
Requires-Dist: standard-aifc
Requires-Dist: setuptools
Requires-Dist: bs4
